MANIFEST.in
README.md
setup.py
colorbm/__init__.py
colorbm/colorbm.py
colorbm.egg-info/PKG-INFO
colorbm.egg-info/SOURCES.txt
colorbm.egg-info/dependency_links.txt
colorbm.egg-info/not-zip-safe
colorbm.egg-info/requires.txt
colorbm.egg-info/top_level.txt
colorbm/diverging/armyrose.rgb
colorbm/diverging/balance.rgb
colorbm/diverging/berlin.rgb
colorbm/diverging/broc.rgb
colorbm/diverging/cet-c1.rgb
colorbm/diverging/cet-c1s.rgb
colorbm/diverging/cet-c2.rgb
colorbm/diverging/cet-c2s.rgb
colorbm/diverging/cet-c4.rgb
colorbm/diverging/cet-c4s.rgb
colorbm/diverging/cet-c5.rgb
colorbm/diverging/cet-c5s.rgb
colorbm/diverging/cet-cbc1.rgb
colorbm/diverging/cet-cbc2.rgb
colorbm/diverging/cet-cbd1.rgb
colorbm/diverging/cet-cbtc1.rgb
colorbm/diverging/cet-cbtc2.rgb
colorbm/diverging/cet-cbtd1.rgb
colorbm/diverging/cet-d1.rgb
colorbm/diverging/cet-d10.rgb
colorbm/diverging/cet-d11.rgb
colorbm/diverging/cet-d12.rgb
colorbm/diverging/cet-d13.rgb
colorbm/diverging/cet-d1a.rgb
colorbm/diverging/cet-d2.rgb
colorbm/diverging/cet-d3.rgb
colorbm/diverging/cet-d4.rgb
colorbm/diverging/cet-d6.rgb
colorbm/diverging/cet-d7.rgb
colorbm/diverging/cet-d8.rgb
colorbm/diverging/cet-d9.rgb
colorbm/diverging/cork.rgb
colorbm/diverging/curl.rgb
colorbm/diverging/delta.rgb
colorbm/diverging/diff.rgb
colorbm/diverging/earth.rgb
colorbm/diverging/fall.rgb
colorbm/diverging/fusion.rgb
colorbm/diverging/geyser.rgb
colorbm/diverging/guppy.rgb
colorbm/diverging/iceburn.rgb
colorbm/diverging/icefire.rgb
colorbm/diverging/lisbon.rgb
colorbm/diverging/oleron.rgb
colorbm/diverging/pride.rgb
colorbm/diverging/redshift.rgb
colorbm/diverging/seasons.rgb
colorbm/diverging/tarn.rgb
colorbm/diverging/tealrose.rgb
colorbm/diverging/temps.rgb
colorbm/diverging/tofino.rgb
colorbm/diverging/topo.rgb
colorbm/diverging/tropic.rgb
colorbm/diverging/vik.rgb
colorbm/diverging/viola.rgb
colorbm/diverging/vlag.rgb
colorbm/diverging/waterlily.rgb
colorbm/diverging/watermelon.rgb
colorbm/diverging/wildfire.rgb
colorbm/palettes/__init__.py
colorbm/palettes/palettes_hex.py
colorbm/sequential/acton.rgb
colorbm/sequential/algae.rgb
colorbm/sequential/amber.rgb
colorbm/sequential/amp.rgb
