Metadata-Version: 2.1
Name: colorbm
Version: 2.0.4
Summary: Color Beyond Matplotlib
Home-page: https://gitee.com/weeshin/colorbm
Author: Wang, Xin
Author-email: xin.wang.418@aliyun.com
License: GPLv3
Platform: UNKNOWN
Requires-Python: >=3.5, <4
